MANIFEST.in
setup.py
src/pingu/__init__.py
src/pingu/main.py
src/pingu/pingu.wsgi
src/pingu.egg-info/PKG-INFO
src/pingu.egg-info/SOURCES.txt
src/pingu.egg-info/dependency_links.txt
src/pingu.egg-info/not-zip-safe
src/pingu.egg-info/requires.txt
src/pingu.egg-info/top_level.txt
src/pingu/heroku/addon-manifest.json
src/pingu/heroku/readme.md
src/pingu/models/__init__.py
src/pingu/models/account.py
src/pingu/models/base.py
src/pingu/models/contact.py
src/pingu/models/log.py
src/pingu/models/server.py
src/pingu/models/task.py
src/pingu/static/css/layout.css
src/pingu/static/css/site.css
src/pingu/static/fonts/pixel_arial.ttf
src/pingu/static/images/favicon.ico
src/pingu/static/images/logo-email.png
src/pingu/static/images/logo-footer-email.png
src/pingu/static/images/logo-footer.png
src/pingu/static/images/site/available-app_store.png
src/pingu/static/images/site/available-google_play.png
src/pingu/static/images/site/available-heroku.png
src/pingu/static/images/site/background.png
src/pingu/static/images/site/badge-uptime.png
src/pingu/static/images/site/banner-trial_included.png
src/pingu/static/images/site/button-check_screenshots.png
src/pingu/static/images/site/button-submit.png
src/pingu/static/images/site/buttons-slideshow.png
src/pingu/static/images/site/dot-green-circle.png
src/pingu/static/images/site/dot-green.png
src/pingu/static/images/site/icon-daily_reports.png
src/pingu/static/images/site/icon-email_notifications.png
src/pingu/static/images/site/icon-iphone_android.png
src/pingu/static/images/site/icon-public_profile.png
src/pingu/static/images/site/icon-rest_api.png
src/pingu/static/images/site/icon-sms_messages.png
src/pingu/static/images/site/icon-web_interface.png
src/pingu/static/images/site/icon-xmpp.png
src/pingu/static/images/site/logo-footer.png
src/pingu/static/images/site/logo-header.png
src/pingu/static/images/site/main-illustration.png
src/pingu/static/images/site/main-logo.png
src/pingu/static/images/site/radio-button.png
src/pingu/static/images/site/separator-vertical.png
src/pingu/static/images/site/textfield-shadow.png
src/pingu/static/js/main.js
src/pingu/static/js/site.js
src/pingu/templates/about.html.tpl
